odoo10_addon_base_import_async-10.0.1.0.0.99.dev4-py2.7-nspkg.pth
odoo/addons/base_import_async/README.rst
odoo/addons/base_import_async/__init__.py
odoo/addons/base_import_async/__manifest__.py
odoo/addons/base_import_async/models/__init__.py
odoo/addons/base_import_async/models/base_import_import.py
odoo/addons/base_import_async/models/queue_job.py
odoo/addons/base_import_async/static/description/icon.png
odoo/addons/base_import_async/static/src/js/import.js
odoo/addons/base_import_async/static/src/xml/import.xml
odoo/addons/base_import_async/views/base_import_async.xml
odoo10_addon_base_import_async-10.0.1.0.0.99.dev4.dist-info/METADATA
odoo10_addon_base_import_async-10.0.1.0.0.99.dev4.dist-info/RECORD
odoo10_addon_base_import_async-10.0.1.0.0.99.dev4.dist-info/WHEEL
odoo10_addon_base_import_async-10.0.1.0.0.99.dev4.dist-info/namespace_packages.txt
odoo10_addon_base_import_async-10.0.1.0.0.99.dev4.dist-info/top_level.txt
